cic/__init__.py
cic/load_clvm.py
cic/cli/__init__.py
cic/cli/clients.py
cic/cli/main.py
cic/cli/record_types.py
cic/cli/sync_store.py
cic/clsp/__init__.py
cic/clsp/drop_coins/__init__.py
cic/clsp/drop_coins/ach_clawback.clsp.hex
cic/clsp/drop_coins/ach_completion.clsp.hex
cic/clsp/drop_coins/p2_merkle_tree.clsp.hex
cic/clsp/drop_coins/p2_new_lock_level.clsp.hex
cic/clsp/drop_coins/rekey_clawback.clsp.hex
cic/clsp/drop_coins/rekey_completion.clsp.hex
cic/clsp/filters/__init__.py
cic/clsp/filters/only_rekey.clsp.hex
cic/clsp/filters/rekey_and_payment.clsp.hex
cic/clsp/include/__init__.py
cic/clsp/singleton/__init__.py
cic/clsp/singleton/prefarm_inner.clsp.hex
cic/clsp/singleton/singleton_top_layer_v1_1.clsp.hex
cic/drivers/__init__.py
cic/drivers/drop_coins.py
cic/drivers/filters.py
cic/drivers/merkle_utils.py
cic/drivers/prefarm.py
cic/drivers/prefarm_info.py
cic/drivers/puzzle_root_construction.py
cic/drivers/singleton.py
chia_internal_custody-0.2.9.dist-info/LICENSE
chia_internal_custody-0.2.9.dist-info/METADATA
chia_internal_custody-0.2.9.dist-info/WHEEL
chia_internal_custody-0.2.9.dist-info/entry_points.txt
chia_internal_custody-0.2.9.dist-info/top_level.txt
chia_internal_custody-0.2.9.dist-info/RECORD
