Metadata-Version: 2.1
Name: chia-internal-custody
Version: 0.2.9
Summary: Custody puzzles and CLI tailored to Chia Network's business and security requirements
Home-page: https://github.com/Chia-Network/internal-custody
Author: Quexington
Author-email: m.hauff@chia.net
License: https://opensource.org/licenses/Apache-2.0
Project-URL: Bug Reports, https://github.com/Chia-Network/internal-custody
Project-URL: Source, https://github.com/Chia-Network/internal-custody
Classifier: Programming Language :: Python :: 3
Classifier: Programming Language :: Python :: 3.6
Classifier: Programming Language :: Python :: 3.7
Classifier: Programming Language :: Python :: 3.8
Classifier: Programming Language :: Python :: 3.9
Classifier: License :: OSI Approved :: Apache Software License
Classifier: Topic :: Security :: Cryptography
License-File: LICENSE
Requires-Dist: chia-blockchain ==1.7.0
Requires-Dist: click ==8.1.3
Requires-Dist: segno ==1.4.1
Requires-Dist: hsms ==0.1.3
Provides-Extra: dev
Requires-Dist: flake8 ; extra == 'dev'
Requires-Dist: mypy ; extra == 'dev'
Requires-Dist: black ==21.12b0 ; extra == 'dev'
Requires-Dist: pytest ; extra == 'dev'
Requires-Dist: pytest-asyncio ; extra == 'dev'
Requires-Dist: pytest-env ; extra == 'dev'
